[
  {
    "type": "mapgen",
    "om_terrain": [ "morlock_lair_mid_e" ],
    "method": "json",
    "weight": 1000,
    "object": {
      "fill_ter": "t_rock_floor",
      "rows": [
        "----,,            ,,----",
        "-###z,,          ,,z###-",
        "-#©©©,            ,©©©#-",
        "-#©©©      ©©      ©©©#-",
        ",z©©©  *   ©©   *  ©©©z,",
        " ,                    ,,",
        "          H  H          ",
        "    *              *    ",
        "        ^      ^     ,  ",
        ",        YYYYYY      ,, ",
        ",     H, YYYYYY  H    ,,",
        " , ©©    YYYYYY    ©©  ,",
        " , ©©    YYYYYY    ©©  ,",
        ",     H, YYYYYY  H    ,,",
        ",        YYYYYY      ,, ",
        "        ^      ^     ,  ",
        "    *              *    ",
        "          H  H          ",
        " ,,               ,,  ,,",
        ",z©©©  *   ©©   *  ©©©z,",
        "-#©©©      ©©      ©©©#-",
        "-#©©©,             ©©©#-",
        "-###z,,           ,z###-",
        "----,             ,,----"
      ],
    "terrain": { " ": [ ["t_rock_floor", 13], ["t_dirt", 2] ] },
      "furniture": { "Y": "f_tatami" },
      "palettes": [ "morlock_lair" ]
    }
  }
]
